zyte_common_items/VERSION
zyte_common_items/__init__.py
zyte_common_items/_addon.py
zyte_common_items/_dateutils.py
zyte_common_items/_examples.py
zyte_common_items/adapter.py
zyte_common_items/ae.py
zyte_common_items/base.py
zyte_common_items/converters.py
zyte_common_items/extractors.py
zyte_common_items/fields.py
zyte_common_items/log_formatters.py
zyte_common_items/pipelines.py
zyte_common_items/processors.py
zyte_common_items/py.typed
zyte_common_items/util.py
zyte_common_items/components/__init__.py
zyte_common_items/components/_compat.py
zyte_common_items/components/additional_property.py
zyte_common_items/components/address.py
zyte_common_items/components/author.py
zyte_common_items/components/brand.py
zyte_common_items/components/breadcrumbs.py
zyte_common_items/components/business_place.py
zyte_common_items/components/forum_thread.py
zyte_common_items/components/gtin.py
zyte_common_items/components/job_posting.py
zyte_common_items/components/links.py
zyte_common_items/components/media.py
zyte_common_items/components/metadata.py
zyte_common_items/components/ratings.py
zyte_common_items/components/real_estate.py
zyte_common_items/components/request.py
zyte_common_items/components/social_media_post.py
zyte_common_items/items/__init__.py
zyte_common_items/items/_compat.py
zyte_common_items/items/article.py
zyte_common_items/items/article_list.py
zyte_common_items/items/article_navigation.py
zyte_common_items/items/business_place.py
zyte_common_items/items/custom_attributes.py
zyte_common_items/items/forum_thread.py
zyte_common_items/items/job_posting.py
zyte_common_items/items/job_posting_navigation.py
zyte_common_items/items/product.py
zyte_common_items/items/product_list.py
zyte_common_items/items/product_navigation.py
zyte_common_items/items/real_estate.py
zyte_common_items/items/search_request_template.py
zyte_common_items/items/serp.py
zyte_common_items/items/social_media_post.py
zyte_common_items/pages/__init__.py
zyte_common_items/pages/article.py
zyte_common_items-0.28.0.dist-info/licenses/LICENSE
zyte_common_items-0.28.0.dist-info/METADATA
zyte_common_items-0.28.0.dist-info/WHEEL
zyte_common_items-0.28.0.dist-info/top_level.txt
zyte_common_items-0.28.0.dist-info/RECORD
